<?xml version="1.0" encoding="UTF-8" standalone="yes"?>
<APIProxy revision="4" name="greeting-w3-light">
    <Basepaths>/greeting</Basepaths>
    <ConfigurationVersion majorVersion="4" minorVersion="0"/>
    <CreatedAt>1592798962671</CreatedAt>
    <CreatedBy>srshetty@hotmail.com</CreatedBy>
    <Description></Description>
    <DisplayName>greeting</DisplayName>
    <LastModifiedAt>1592798962671</LastModifiedAt>
    <LastModifiedBy>srshetty@hotmail.com</LastModifiedBy>
    <ManifestVersion>SHA-512:cb3fafc6ac1a9372420a524f17c84dee9776a24c65d8cfb8cf89f956174e9e758e3819cb8b913242abe69822d0164a9f1b0eda6b887a0b594e96ff5637c87071</ManifestVersion>
    <Policies>
        <Policy>NRTracePrepare</Policy>
        <Policy>NRTraceReceiver</Policy>
        <Policy>NewRelicAPI</Policy>
    </Policies>
    <ProxyEndpoints>
        <ProxyEndpoint>default</ProxyEndpoint>
    </ProxyEndpoints>
    <Resources>
        <Resource>jsc://NRTracePrepare.js</Resource>
        <Resource>jsc://NRTraceReceiver.js</Resource>
    </Resources>
    <Spec></Spec>
    <TargetServers/>
    <TargetEndpoints>
        <TargetEndpoint>default</TargetEndpoint>
    </TargetEndpoints>
</APIProxy>
